manifestly/__init__.py
manifestly/cli.py
manifestly/core.py
manifestly/settings.py
tests/__init__.py
tests/test_cli.py
tests/test_manifests.py
manifestly-0.2.4.dist-info/LICENSE
manifestly-0.2.4.dist-info/METADATA
manifestly-0.2.4.dist-info/WHEEL
manifestly-0.2.4.dist-info/top_level.txt
manifestly-0.2.4.dist-info/RECORD
