Metadata-Version: 2.1
Name: manifestly
Version: 0.2.4
Summary: Manifestly is a Python package designed to generate a manifest of a directory's contents, capturing file paths and their corresponding hashes. This allows for precise synchronization between two directories based on their content, ensuring that only files with differences in content are synchronized. This package provides a reliable solution for tracking and managing file changes efficiently.
Home-page: https://github.com/gdoermann/manifestly
Author: Greg Doermann
Author-email: manifestly@doermann.me
License: MIT
Project-URL: Source, https://github.com/gdoermann/manifestly
Project-URL: Tracker, https://github.com/gdoermann/manifestly/issues
Classifier: Development Status :: 4 - Beta
Classifier: Intended Audience :: Developers
Classifier: License :: OSI Approved :: MIT License
Classifier: Operating System :: OS Independent
Classifier: Programming Language :: Python :: 3.8
Classifier: Programming Language :: Python :: 3.9
Classifier: Programming Language :: Python :: 3.10
Classifier: Programming Language :: Python :: 3.11
Classifier: Programming Language :: Python :: 3.12
Classifier: Programming Language :: Python :: 3.13
Classifier: Topic :: Software Development :: Libraries :: Python Modules
Requires-Python: >=3.8
License-File: LICENSE
Requires-Dist: click
Requires-Dist: fsspec
Provides-Extra: aws
Requires-Dist: s3fs; extra == "aws"
Requires-Dist: boto3; extra == "aws"
Requires-Dist: botocore; extra == "aws"
Provides-Extra: gcs
Requires-Dist: gcsfs; extra == "gcs"
Requires-Dist: google-cloud-storage; extra == "gcs"
Provides-Extra: azure
Requires-Dist: adlfs; extra == "azure"
Requires-Dist: azure-storage-blob; extra == "azure"
Provides-Extra: extras
Requires-Dist: tox~=4.14.2; extra == "extras"
Requires-Dist: wheel; extra == "extras"
Requires-Dist: ipython; extra == "extras"
Requires-Dist: flake8~=6.0.0; extra == "extras"
Requires-Dist: twine; extra == "extras"
Requires-Dist: pytest; extra == "extras"
Requires-Dist: pip-tools; extra == "extras"
Requires-Dist: bumpver; extra == "extras"
Requires-Dist: coverage; extra == "extras"
